{
  "name": "tenant-c",
  "description": "Edge-case coverage tenant. Every Graph CA policy shape we know about appears at least once: country named-location includes, IP named-location excludes, app filters, device platform conditions, sign-in frequency controls, persistent browser session controls, AND/OR grant combinations, workload identity policies, and role-scoped policies for Global Admin and Privileged Role Admin.",
  "tenant_id": "00000000-cccc-3333-3333-333333333333",
  "scenario_tags": [
    "edge-cases",
    "every-shape",
    "role-scoped",
    "workload-identity"
  ],
  "expected_findings": {
    "total": 10,
    "by_category": {
      "coverage": 2,
      "rule": 5,
      "exclusion": 3
    },
    "by_severity": {
      "critical": 0,
      "high": 4,
      "medium": 3,
      "low": 3,
      "info": 0
    },
    "by_rule_id": {
      "coverage.all_users-on-legacy_auth": 1,
      "coverage.guests-on-legacy_auth": 1,
      "exclusion.undocumented": 3,
      "rule.block-legacy-auth": 1,
      "rule.device-compliance-sensitive-apps": 1,
      "rule.guest-restrictions": 1,
      "rule.risk-based-signin": 1,
      "rule.risk-based-user": 1
    }
  },
  "calibrated_at": "2026-04-28",
  "notes": "calibrated against rules engine v0.0.1; every Graph shape parses without rule crashes.",
  "signin_scenarios": [
    {
      "name": "baseline",
      "description": "30 days of normal behaviour, no injected anomalies.",
      "signins_path": "signins/baseline/signins.json",
      "ground_truth_path": "signins/baseline/ground_truth.json"
    },
    {
      "name": "replay-attacks",
      "description": "Baseline plus scripted impossible-travel, MFA bypass, off-hours admin, credential stuffing, new ASN.",
      "signins_path": "signins/replay-attacks/signins.json",
      "ground_truth_path": "signins/replay-attacks/ground_truth.json"
    },
    {
      "name": "noisy",
      "description": "Operationally noisy normals plus the same scripted attacks.",
      "signins_path": "signins/noisy/signins.json",
      "ground_truth_path": "signins/noisy/ground_truth.json"
    }
  ],
  "anomaly_calibration": {
    "model_version": "signalguard-anomaly-pooled-00000000-cccc-3333-3333-333333333333:v1",
    "pipeline": "StandardScaler -> IsolationForest(n=200, random_state=42) + rule-based score booster",
    "contamination": 0.05,
    "feature_count": 20,
    "scenarios": {
      "baseline": {
        "rows": 4459,
        "flagged": 201,
        "flagged_high": 68,
        "gt": 0,
        "tp": 0,
        "precision": null,
        "recall": null,
        "f1": null,
        "false_positive_rate": 0.015
      },
      "replay-attacks": {
        "rows": 4461,
        "flagged": 249,
        "flagged_high": 88,
        "gt": 27,
        "tp": 24,
        "precision": 0.273,
        "recall": 0.889,
        "f1": 0.417,
        "false_positive_rate": 0.014
      },
      "noisy": {
        "rows": 4522,
        "flagged": 295,
        "flagged_high": 95,
        "gt": 27,
        "tp": 23,
        "precision": 0.242,
        "recall": 0.852,
        "f1": 0.377,
        "false_positive_rate": 0.016
      }
    },
    "calibrated_at": "2026-04-29",
    "notes": "highest sign-in volume; off-hours admin event still missed in noisy because the user is a tier-0 admin with broader work-hour distribution from the noise injection."
  }
}
